[
	{
		"de": "abgeben",
		"gsw": "abgeh"
	},
	{
		"de": "abgehen (sie)",
		"gsw": "abgönd"
	},
	{
		"de": "abgesehen",
		"gsw": "abgseh"
	},
	{
		"de": "Abteilung",
		"gsw": "Abteilig"
	},
	{
		"de": "als",
		"gsw": "als"
	},
	{
		"de": "als",
		"gsw": "als"
	},
	{
		"de": "also",
		"gsw": "aso"
	},
	{
		"de": "an",
		"gsw": "a"
	},
	{
		"de": "an",
		"gsw": "a"
	},
	{
		"de": "Analytiker",
		"gsw": "Analytiker"
	},
	{
		"de": "anderem",
		"gsw": "anderem"
	},
	{
		"de": "anonym",
		"gsw": "anonym"
	},
	{
		"de": "Arbeit",
		"gsw": "Arbeit"
	},
	{
		"de": "arbeite (ich)",
		"gsw": "schaffe"
	},
	{
		"de": "Arbeitgeber",
		"gsw": "Arbeitgeber"
	},
	{
		"de": "Ärzte",
		"gsw": "Ärzt"
	},
	{
		"de": "Ärzte",
		"gsw": "Ärzte"
	},
	{
		"de": "Aspekt",
		"gsw": "Aspekt"
	},
	{
		"de": "auch",
		"gsw": "au"
	},
	{
		"de": "auch",
		"gsw": "au"
	},
	{
		"de": "Augen",
		"gsw": "Auge"
	},
	{
		"de": "aus",
		"gsw": "uus"
	},
	{
		"de": "ausgeben (sie)",
		"gsw": "usegebed"
	},
	{
		"de": "ausgegeben",
		"gsw": "usegeh"
	},
	{
		"de": "bei",
		"gsw": "bi"
	},
	{
		"de": "bin",
		"gsw": "bin"
	},
	{
		"de": "biomedizinischer",
		"gsw": "biomedizinische"
	},
	{
		"de": "chan",
		"gsw": "kann"
	},
	{
		"de": "Corona",
		"gsw": "Corona"
	},
	{
		"de": "Corona-Test",
		"gsw": "Coronatest"
	},
	{
		"de": "Corona-Tests",
		"gsw": "Coronatests"
	},
	{
		"de": "da",
		"gsw": "da"
	},
	{
		"de": "da",
		"gsw": "do"
	},
	{
		"de": "da",
		"gsw": "do"
	},
	{
		"de": "da",
		"gsw": "do"
	},
	{
		"de": "damit",
		"gsw": "damit"
	},
	{
		"de": "das",
		"gsw": "da"
	},
	{
		"de": "das",
		"gsw": "das"
	},
	{
		"de": "das",
		"gsw": "s"
	},
	{
		"de": "das",
		"gsw": "s"
	},
	{
		"de": "das",
		"gsw": "s"
	},
	{
		"de": "dass",
		"gsw": "das"
	},
	{
		"de": "dass",
		"gsw": "dass"
	},
	{
		"de": "dass",
		"gsw": "dass"
	},
	{
		"de": "dass",
		"gsw": "dass"
	},
	{
		"de": "dass ich",
		"gsw": "dassi"
	},
	{
		"de": "davon",
		"gsw": "devo"
	},
	{
		"de": "dein (M)",
		"gsw": "din"
	},
	{
		"de": "deine",
		"gsw": "dini"
	},
	{
		"de": "dem",
		"gsw": "de"
	},
	{
		"de": "dem",
		"gsw": "de"
	},
	{
		"de": "den",
		"gsw": "de"
	},
	{
		"de": "den",
		"gsw": "de"
	},
	{
		"de": "den",
		"gsw": "de"
	},
	{
		"de": "den",
		"gsw": "de"
	},
	{
		"de": "den",
		"gsw": "de"
	},
	{
		"de": "denn",
		"gsw": "denn"
	},
	{
		"de": "der",
		"gsw": "de"
	},
	{
		"de": "der",
		"gsw": "de"
	},
	{
		"de": "der",
		"gsw": "de"
	},
	{
		"de": "der",
		"gsw": "wo"
	},
	{
		"de": "Details",
		"gsw": "Details"
	},
	{
		"de": "dich",
		"gsw": "dich"
	},
	{
		"de": "die",
		"gsw": "d"
	},
	{
		"de": "die",
		"gsw": "die"
	},
	{
		"de": "die",
		"gsw": "die"
	},
	{
		"de": "die",
		"gsw": "die"
	},
	{
		"de": "die",
		"gsw": "die"
	},
	{
		"de": "die",
		"gsw": "wo"
	},
	{
		"de": "dir",
		"gsw": "dir"
	},
	{
		"de": "dort",
		"gsw": "dört"
	},
	{
		"de": "dort",
		"gsw": "döt"
	},
	{
		"de": "du",
		"gsw": "du"
	},
	{
		"de": "eigenen",
		"gsw": "eigene"
	},
	{
		"de": "eigenen",
		"gsw": "eigete"
	},
	{
		"de": "ein paar",
		"gsw": "paar"
	},
	{
		"de": "einfach",
		"gsw": "afoch"
	},
	{
		"de": "einfach",
		"gsw": "afoch"
	},
	{
		"de": "er",
		"gsw": "er"
	},
	{
		"de": "erste",
		"gsw": "erst"
	},
	{
		"de": "erste",
		"gsw": "erst"
	},
	{
		"de": "erübrigt (er/sie/es)",
		"gsw": "erübrigt"
	},
	{
		"de": "erwähnt",
		"gsw": "erwähnt"
	},
	{
		"de": "es",
		"gsw": "es"
	},
	{
		"de": "ethisch",
		"gsw": "ethisch"
	},
	{
		"de": "ethischen",
		"gsw": "ethische"
	},
	{
		"de": "Fälschung",
		"gsw": "Fälschig"
	},
	{
		"de": "Ferien",
		"gsw": "Ferie"
	},
	{
		"de": "Ferien",
		"gsw": "Ferie"
	},
	{
		"de": "für",
		"gsw": "für"
	},
	{
		"de": "gar",
		"gsw": "ger"
	},
	{
		"de": "gefährden",
		"gsw": "gfährde"
	},
	{
		"de": "Gefühl",
		"gsw": "Gfühl"
	},
	{
		"de": "gehen",
		"gsw": "go"
	},
	{
		"de": "gehen",
		"gsw": "goh"
	},
	{
		"de": "gehen",
		"gsw": "goh"
	},
	{
		"de": "gehört",
		"gsw": "ghört"
	},
	{
		"de": "gelöscht",
		"gsw": "glöscht"
	},
	{
		"de": "genauer",
		"gsw": "genauer"
	},
	{
		"de": "genauso",
		"gsw": "genauso"
	},
	{
		"de": "genauso",
		"gsw": "genauso"
	},
	{
		"de": "gerne",
		"gsw": "gern"
	},
	{
		"de": "Geschäft",
		"gsw": "Gschäft"
	},
	{
		"de": "Geschäftsleitung",
		"gsw": "Gschäftsleitig"
	},
	{
		"de": "gesehen",
		"gsw": "gseh"
	},
	{
		"de": "gesehen",
		"gsw": "gseh"
	},
	{
		"de": "gewesen",
		"gsw": "gsi"
	},
	{
		"de": "gewesen",
		"gsw": "gsi"
	},
	{
		"de": "gibt",
		"gsw": "git"
	},
	{
		"de": "Grenzen",
		"gsw": "Grenze"
	},
	{
		"de": "habe (ich)",
		"gsw": "ha"
	},
	{
		"de": "habe (ich)",
		"gsw": "ha"
	},
	{
		"de": "habe (ich)",
		"gsw": "han"
	},
	{
		"de": "habe ich",
		"gsw": "hani"
	},
	{
		"de": "haben (sie)",
		"gsw": "hend"
	},
	{
		"de": "haben wir",
		"gsw": "hemmer"
	},
	{
		"de": "hallo",
		"gsw": "hallo"
	},
	{
		"de": "halt",
		"gsw": "halt"
	},
	{
		"de": "hat (er/sie/es)",
		"gsw": "het"
	},
	{
		"de": "heute",
		"gsw": "hüt"
	},
	{
		"de": "Hinweise",
		"gsw": "Hiiwiis"
	},
	{
		"de": "ich",
		"gsw": "i"
	},
	{
		"de": "ich",
		"gsw": "i"
	},
	{
		"de": "ich",
		"gsw": "i"
	},
	{
		"de": "ich",
		"gsw": "ich"
	},
	{
		"de": "ich",
		"gsw": "ich"
	},
	{
		"de": "in",
		"gsw": "i"
	},
	{
		"de": "in",
		"gsw": "i"
	},
	{
		"de": "in die",
		"gsw": "id"
	},
	{
		"de": "in die",
		"gsw": "id"
	},
	{
		"de": "in einem",
		"gsw": "imne"
	},
	{
		"de": "ist (er/sie/es)",
		"gsw": "isch"
	},
	{
		"de": "ist (er/sie/es)",
		"gsw": "isch"
	},
	{
		"de": "ist (er/sie/es)",
		"gsw": "isch"
	},
	{
		"de": "ist (er/sie/es)",
		"gsw": "isch"
	},
	{
		"de": "ja",
		"gsw": "jo"
	},
	{
		"de": "Jahren",
		"gsw": "Johr"
	},
	{
		"de": "Job",
		"gsw": "Job"
	},
	{
		"de": "kann (er/sie/es)",
		"gsw": "chan"
	},
	{
		"de": "kann (ich)",
		"gsw": "chan"
	},
	{
		"de": "kannst (du)",
		"gsw": "chasch"
	},
	{
		"de": "Kanton",
		"gsw": "Kanton"
	},
	{
		"de": "keine",
		"gsw": "kei"
	},
	{
		"de": "kenne (ich)",
		"gsw": "kenn"
	},
	{
		"de": "Kontakt",
		"gsw": "Kontakt"
	},
	{
		"de": "korrupt",
		"gsw": "korrupt"
	},
	{
		"de": "Kunde",
		"gsw": "Chund"
	},
	{
		"de": "Kunde",
		"gsw": "Chund"
	},
	{
		"de": "Labor",
		"gsw": "Labor"
	},
	{
		"de": "Laborauftrag",
		"gsw": "Laboruftrag"
	},
	{
		"de": "lassen",
		"gsw": "loh"
	},
	{
		"de": "Leitung",
		"gsw": "Leitig"
	},
	{
		"de": "machen",
		"gsw": "mache"
	},
	{
		"de": "machen (wir)",
		"gsw": "mached"
	},
	{
		"de": "machen (wir)",
		"gsw": "mached"
	},
	{
		"de": "macht (er/sie/es)",
		"gsw": "macht"
	},
	{
		"de": "mal",
		"gsw": "mol"
	},
	{
		"de": "mal",
		"gsw": "mol"
	},
	{
		"de": "Mal",
		"gsw": "Mol"
	},
	{
		"de": "meinem",
		"gsw": "mim"
	},
	{
		"de": "melden",
		"gsw": "melde"
	},
	{
		"de": "mich",
		"gsw": "mi"
	},
	{
		"de": "mich",
		"gsw": "mi"
	},
	{
		"de": "mich",
		"gsw": "mich"
	},
	{
		"de": "mit",
		"gsw": "mit"
	},
	{
		"de": "mit",
		"gsw": "mit"
	},
	{
		"de": "müssen wir",
		"gsw": "müremer"
	},
	{
		"de": "musst (du)",
		"gsw": "muesch"
	},
	{
		"de": "musst (du)",
		"gsw": "muesch"
	},
	{
		"de": "negativ",
		"gsw": "negativ"
	},
	{
		"de": "nicht",
		"gsw": "ned"
	},
	{
		"de": "nicht",
		"gsw": "ned"
	},
	{
		"de": "nicht",
		"gsw": "ned"
	},
	{
		"de": "nicht",
		"gsw": "ned"
	},
	{
		"de": "noch",
		"gsw": "no"
	},
	{
		"de": "oder",
		"gsw": "oder"
	},
	{
		"de": "ohne",
		"gsw": "ohni"
	},
	{
		"de": "ohne",
		"gsw": "ohni"
	},
	{
		"de": "Option",
		"gsw": "Option"
	},
	{
		"de": "passiert (er/sie/es)",
		"gsw": "passiert"
	},
	{
		"de": "Patient",
		"gsw": "Patient"
	},
	{
		"de": "Patient",
		"gsw": "Patient"
	},
	{
		"de": "positiv",
		"gsw": "positiv"
	},
	{
		"de": "positiv",
		"gsw": "positiv"
	},
	{
		"de": "Programm",
		"gsw": "Programm"
	},
	{
		"de": "recht",
		"gsw": "recht"
	},
	{
		"de": "rechtlich",
		"gsw": "rechtlich"
	},
	{
		"de": "reden",
		"gsw": "rede"
	},
	{
		"de": "reden",
		"gsw": "rede"
	},
	{
		"de": "relativ",
		"gsw": "relativ"
	},
	{
		"de": "Resultate",
		"gsw": "Resultat"
	},
	{
		"de": "Resultatfälschung",
		"gsw": "Resultatfälschig"
	},
	{
		"de": "Sachen",
		"gsw": "Sache"
	},
	{
		"de": "Sachen",
		"gsw": "Sache"
	},
	{
		"de": "sauer",
		"gsw": "sauer"
	},
	{
		"de": "schon",
		"gsw": "scho"
	},
	{
		"de": "sich",
		"gsw": "sich"
	},
	{
		"de": "sicher",
		"gsw": "sicher"
	},
	{
		"de": "sind (sie)",
		"gsw": "sind"
	},
	{
		"de": "so",
		"gsw": "so"
	},
	{
		"de": "so",
		"gsw": "so"
	},
	{
		"de": "so",
		"gsw": "so"
	},
	{
		"de": "so ein (N)",
		"gsw": "sones"
	},
	{
		"de": "so was",
		"gsw": "sowas"
	},
	{
		"de": "sonst",
		"gsw": "susch"
	},
	{
		"de": "stehen",
		"gsw": "stoh"
	},
	{
		"de": "suchen",
		"gsw": "sueche"
	},
	{
		"de": "überhaupt",
		"gsw": "überhaupt"
	},
	{
		"de": "und",
		"gsw": "und"
	},
	{
		"de": "und",
		"gsw": "und"
	},
	{
		"de": "und",
		"gsw": "und"
	},
	{
		"de": "und",
		"gsw": "und"
	},
	{
		"de": "und",
		"gsw": "und"
	},
	{
		"de": "und",
		"gsw": "und"
	},
	{
		"de": "und",
		"gsw": "und"
	},
	{
		"de": "uns",
		"gsw": "üs"
	},
	{
		"de": "unter",
		"gsw": "unter"
	},
	{
		"de": "vo",
		"gsw": "vo"
	},
	{
		"de": "von",
		"gsw": "vo"
	},
	{
		"de": "von",
		"gsw": "vo"
	},
	{
		"de": "von",
		"gsw": "vo"
	},
	{
		"de": "von",
		"gsw": "vu"
	},
	{
		"de": "von einem",
		"gsw": "vomne"
	},
	{
		"de": "war (er/sie/es)",
		"gsw": "gsi isch"
	},
	{
		"de": "was",
		"gsw": "wa"
	},
	{
		"de": "was ich",
		"gsw": "wani"
	},
	{
		"de": "weiss (ich)",
		"gsw": "weiss"
	},
	{
		"de": "welche",
		"gsw": "welle"
	},
	{
		"de": "welches",
		"gsw": "wo"
	},
	{
		"de": "wenden",
		"gsw": "wendä"
	},
	{
		"de": "wenn",
		"gsw": "wenn"
	},
	{
		"de": "Whistleblower",
		"gsw": "Whistleblower"
	},
	{
		"de": "wie",
		"gsw": "wie"
	},
	{
		"de": "wie",
		"gsw": "wie"
	},
	{
		"de": "wie",
		"gsw": "wie"
	},
	{
		"de": "will (ich)",
		"gsw": "will"
	},
	{
		"de": "wir",
		"gsw": "mir"
	},
	{
		"de": "wir",
		"gsw": "mir"
	},
	{
		"de": "wissen",
		"gsw": "wüsse"
	},
	{
		"de": "wozu",
		"gsw": "wozue"
	},
	{
		"de": "würde (ich)",
		"gsw": "wür"
	},
	{
		"de": "würde (ich)",
		"gsw": "würd"
	},
	{
		"de": "würde ich",
		"gsw": "wöri"
	},
	{
		"de": "zu",
		"gsw": "z"
	},
	{
		"de": "zum Beispiel",
		"gsw": "zum Bispil"
	},
	{
		"de": "zusammen",
		"gsw": "zame"
	}
]
