[{"src":"abbeissen","target":[{"translation":"abbisse","count":1}]},{"src":"aber","target":[{"translation":"Aber","count":1},{"translation":"aber","count":1}]},{"src":"abknabbern","target":[{"translation":"abknabbere","count":1}]},{"src":"Abstand","target":[{"translation":"Abstand","count":1}]},{"src":"achtung","target":[{"translation":"Achtig","count":1}]},{"src":"als","target":[{"translation":"als","count":1}]},{"src":"als ein (N)","target":[{"translation":"wie n e","count":1}]},{"src":"also","target":[{"translation":"also","count":1}]},{"src":"Amerika","target":[{"translation":"Amerika","count":1}]},{"src":"an","target":[{"translation":"an","count":1}]},{"src":"ändert (ihr)","target":[{"translation":"änderet","count":1}]},{"src":"Ärger","target":[{"translation":"Lämpe","count":1}]},{"src":"auch","target":[{"translation":"au","count":2}]},{"src":"aufpassen","target":[{"translation":"Uffpasse","count":1}]},{"src":"aus","target":[{"translation":"us","count":1}]},{"src":"Auslandbünzli","target":[{"translation":"Uslandbünzli","count":1}]},{"src":"ausnahmsweise","target":[{"translation":"usnahmswiis","count":1}]},{"src":"aussprechen","target":[{"translation":"usschwätze","count":1}]},{"src":"Auto","target":[{"translation":"Auto","count":1}]},{"src":"Basel","target":[{"translation":"Basel","count":2}]},{"src":"bei","target":[{"translation":"bi","count":3}]},{"src":"beides","target":[{"translation":"beides","count":1}]},{"src":"besser","target":[{"translation":"besser","count":1}]},{"src":"besten (pl.)","target":[{"translation":"beschte","count":1}]},{"src":"bist (du)","target":[{"translation":"bisch","count":1}]},{"src":"Bock","target":[{"translation":"Bock","count":1}]},{"src":"braucht (er/sie/es)","target":[{"translation":"brucht","count":1}]},{"src":"Brokkolisüppchen","target":[{"translation":"Brokkolisüppli","count":1}]},{"src":"Bündner","target":[{"translation":"Büdner","count":1}]},{"src":"dann","target":[{"translation":"denn","count":2}]},{"src":"das","target":[{"translation":"das","count":1}]},{"src":"dass","target":[{"translation":"das","count":2}]},{"src":"de (M)","target":[{"translation":"dr","count":1}]},{"src":"dem","target":[{"translation":"däm","count":1}]},{"src":"den (M)","target":[{"translation":"dr","count":1}]},{"src":"den (pl.)","target":[{"translation":"de","count":2}]},{"src":"der","target":[{"translation":"dr","count":1}]},{"src":"der (M)","target":[{"translation":"dr","count":1}]},{"src":"Deutscher in der Schweiz (abwertend)","target":[{"translation":"Gummihals","count":1}]},{"src":"die","target":[{"translation":"wo","count":1}]},{"src":"die (F)","target":[{"translation":"d","count":3}]},{"src":"die (pl.)","target":[{"translation":"die","count":1},{"translation":"Die","count":1},{"translation":"wo","count":1}]},{"src":"doch","target":[{"translation":"doch","count":3}]},{"src":"drin","target":[{"translation":"dinne","count":1}]},{"src":"du","target":[{"translation":"du","count":2}]},{"src":"durchsetzt (ihr)","target":[{"translation":"duuresetzet","count":1}]},{"src":"Edit","target":[{"translation":"edit","count":1}]},{"src":"egal","target":[{"translation":"egal","count":1}]},{"src":"ehrlich","target":[{"translation":"ehrlich","count":1}]},{"src":"Eigenwerbung","target":[{"translation":"Sälbstpromotion","count":1}]},{"src":"ein","target":[{"translation":"ei","count":1}]},{"src":"ein (N)","target":[{"translation":"es","count":1}]},{"src":"ein bisschen","target":[{"translation":"e weneli","count":1}]},{"src":"eine (F)","target":[{"translation":"e","count":2},{"translation":"eine","count":1},{"translation":"ne","count":1}]},{"src":"einfach","target":[{"translation":"eifach","count":1}]},{"src":"einkaufen","target":[{"translation":"kommissione mache","count":1}]},{"src":"einkauft (er/sie/es)","target":[{"translation":"yykauft","count":1}]},{"src":"einstehen","target":[{"translation":"Yystoh","count":1}]},{"src":"ekelhaft","target":[{"translation":"oltig","count":1}]},{"src":"er","target":[{"translation":"Är","count":1},{"translation":"är","count":1}]},{"src":"es","target":[{"translation":"es","count":1}]},{"src":"etwas","target":[{"translation":"ebbis","count":1}]},{"src":"existiere (ich)","target":[{"translation":"existier","count":1}]},{"src":"feines","target":[{"translation":"feins","count":1}]},{"src":"Fertigsüppchen","target":[{"translation":"fertigsüppli","count":1}]},{"src":"finde ich es","target":[{"translation":"findis","count":1}]},{"src":"fragt (er/sie/es)","target":[{"translation":"frogt","count":1}]},{"src":"für","target":[{"translation":"für","count":1}]},{"src":"ganzen (pl.)","target":[{"translation":"ganze","count":1}]},{"src":"geht (er/sie/es)","target":[{"translation":"got","count":1}]},{"src":"geil","target":[{"translation":"geil","count":1}]},{"src":"gerade","target":[{"translation":"grad","count":1}]},{"src":"geriebenem","target":[{"translation":"griebenem","count":1}]},{"src":"gerne","target":[{"translation":"gärn","count":1}]},{"src":"Gerstensuppe","target":[{"translation":"Gärschtesuppe","count":1}]},{"src":"gewusst","target":[{"translation":"gwüsst","count":1}]},{"src":"Grenze","target":[{"translation":"Gränze","count":1}]},{"src":"habe (ich)","target":[{"translation":"Han","count":1},{"translation":"han","count":1}]},{"src":"haben","target":[{"translation":"ha","count":1}]},{"src":"hart","target":[{"translation":"hart","count":1}]},{"src":"hat (er/sie/es)","target":[{"translation":"het","count":1}]},{"src":"hausgemachte (F)","target":[{"translation":"huusgmachti","count":1}]},{"src":"heisse (F)","target":[{"translation":"heissi","count":1}]},{"src":"hier","target":[{"translation":"do","count":1}]},{"src":"ich","target":[{"translation":"Y","count":1},{"translation":"y","count":1}]},{"src":"ihr (pl.)","target":[{"translation":"ihr","count":1}]},{"src":"im","target":[{"translation":"im","count":2}]},{"src":"importieren","target":[{"translation":"importiere","count":1}]},{"src":"in","target":[{"translation":"in","count":1},{"translation":"z","count":1}]},{"src":"in den","target":[{"translation":"in","count":1}]},{"src":"Irland","target":[{"translation":"Irland","count":1}]},{"src":"ist (er/sie/es)","target":[{"translation":"isch","count":4}]},{"src":"ist das","target":[{"translation":"ischs","count":1}]},{"src":"jedem","target":[{"translation":"jedem","count":1}]},{"src":"jemandem","target":[{"translation":"öbberem","count":1}]},{"src":"jetzt","target":[{"translation":"Jetzt","count":1}]},{"src":"Kamerad","target":[{"translation":"Kamerad","count":1}]},{"src":"kapitalistisch","target":[{"translation":"kapitalistisch","count":1}]},{"src":"Käse","target":[{"translation":"kääs","count":1}]},{"src":"keine (F)","target":[{"translation":"kei","count":1}]},{"src":"keinen","target":[{"translation":"kei","count":1}]},{"src":"Kind","target":[{"translation":"Kind","count":1}]},{"src":"Kleinbasel","target":[{"translation":"Kleibasel","count":1}]},{"src":"Kommentar","target":[{"translation":"Kommentar","count":1}]},{"src":"könnte (er/sie/es)","target":[{"translation":"könnt","count":1}]},{"src":"Laden","target":[{"translation":"Lade","count":1}]},{"src":"lass (du)","target":[{"translation":"loss","count":1}]},{"src":"Leben","target":[{"translation":"läbe","count":1}]},{"src":"Lebkuchen","target":[{"translation":"Bieberli","count":1}]},{"src":"liebe (F)","target":[{"translation":"liebi","count":1}]},{"src":"macht (er/sie/es)","target":[{"translation":"macht","count":1}]},{"src":"Mal","target":[{"translation":"mol","count":1}]},{"src":"mal","target":[{"translation":"mol","count":1}]},{"src":"man","target":[{"translation":"me","count":2}]},{"src":"Marsch","target":[{"translation":"Marsch","count":1}]},{"src":"Mehlsuppe","target":[{"translation":"Mählsuppe","count":2}]},{"src":"meist","target":[{"translation":"meist","count":1}]},{"src":"Migros","target":[{"translation":"Migros","count":1}]},{"src":"mit","target":[{"translation":"mit","count":2},{"translation":"mr","count":1}]},{"src":"mitgeflutet","target":[{"translation":"mitgfluetet","count":1}]},{"src":"möchte (er/sie/es)","target":[{"translation":"möcht","count":1}]},{"src":"Motorwagen","target":[{"translation":"Motorwage","count":1}]},{"src":"nehmen","target":[{"translation":"näh","count":1}]},{"src":"nicht","target":[{"translation":"nid","count":7}]},{"src":"niemand","target":[{"translation":"niemer","count":1}]},{"src":"noch mal","target":[{"translation":"nomol","count":1}]},{"src":"nur","target":[{"translation":"nur","count":1}]},{"src":"oder","target":[{"translation":"oder","count":1}]},{"src":"Patent","target":[{"translation":"Patänt","count":1}]},{"src":"Person","target":[{"translation":"Person","count":1}]},{"src":"Pfosten","target":[{"translation":"pfoschte","count":1}]},{"src":"Problem","target":[{"translation":"Problem","count":1}]},{"src":"Recht","target":[{"translation":"rächt","count":1}]},{"src":"Regeln","target":[{"translation":"Regle","count":1}]},{"src":"richtig","target":[{"translation":"richtig","count":1}]},{"src":"Roboter","target":[{"translation":"Roboter","count":1}]},{"src":"runtergewählten","target":[{"translation":"abegwählti","count":1}]},{"src":"Sachen","target":[{"translation":"Sache","count":1}]},{"src":"sagen (wir)","target":[{"translation":"saage","count":1}]},{"src":"sagen wir","target":[{"translation":"sagemer","count":1}]},{"src":"sagst (du)","target":[{"translation":"seisch","count":1}]},{"src":"Schaffhausen","target":[{"translation":"Schaffhuuse","count":1}]},{"src":"scheiss","target":[{"translation":"schiss","count":1}]},{"src":"Schokolade","target":[{"translation":"schoggi","count":1}]},{"src":"schon","target":[{"translation":"scho","count":1}]},{"src":"Schuhe","target":[{"translation":"Schueh","count":1}]},{"src":"Schutz","target":[{"translation":"Schutz","count":1}]},{"src":"schwierig","target":[{"translation":"schwierig","count":1}]},{"src":"sicher","target":[{"translation":"sicher","count":1}]},{"src":"sie (F)","target":[{"translation":"sie","count":1}]},{"src":"sie (pl.)","target":[{"translation":"si","count":1}]},{"src":"sind (sie)","target":[{"translation":"sind","count":1},{"translation":"sinn","count":1}]},{"src":"so","target":[{"translation":"So","count":1},{"translation":"so","count":1}]},{"src":"Spass","target":[{"translation":"spass","count":1}]},{"src":"Tippfehler","target":[{"translation":"typfääler","count":1}]},{"src":"traurige (pl.)","target":[{"translation":"truurigi","count":1}]},{"src":"trinken (langsam)","target":[{"translation":"süppele","count":1}]},{"src":"trinkt langsam (er)","target":[{"translation":"süppelet","count":1}]},{"src":"tut (er/sie/es)","target":[{"translation":"duet","count":1}]},{"src":"um zu","target":[{"translation":"Zum","count":1}]},{"src":"und","target":[{"translation":"und","count":3}]},{"src":"uns","target":[{"translation":"uns","count":1}]},{"src":"unterwasser","target":[{"translation":"unterwasser","count":1}]},{"src":"Versicherung","target":[{"translation":"Versicherig","count":1}]},{"src":"viel","target":[{"translation":"vill","count":1}]},{"src":"vieles","target":[{"translation":"vieles","count":1}]},{"src":"von","target":[{"translation":"Vo","count":1},{"translation":"vo","count":2}]},{"src":"Vorschlag","target":[{"translation":"Vorschlag","count":1}]},{"src":"vorwärts","target":[{"translation":"vorwärts","count":1}]},{"src":"wahrschreinlich","target":[{"translation":"Wohrschins","count":1}]},{"src":"warum","target":[{"translation":"Worum","count":2}]},{"src":"was","target":[{"translation":"was","count":2}]},{"src":"weich","target":[{"translation":"weich","count":1}]},{"src":"weiss (er/sie/es)","target":[{"translation":"weiss","count":1}]},{"src":"welches","target":[{"translation":"wo","count":1}]},{"src":"wenn","target":[{"translation":"Wenn","count":1}]},{"src":"wer","target":[{"translation":"wo","count":1}]},{"src":"Westen","target":[{"translation":"weschte","count":1}]},{"src":"wie","target":[{"translation":"wie","count":2}]},{"src":"wie eine","target":[{"translation":"wie n e","count":1}]},{"src":"wie viel","target":[{"translation":"Wiviel","count":1}]},{"src":"wiederholst (du)","target":[{"translation":"wiederholsch","count":1}]},{"src":"wieso","target":[{"translation":"Wiso","count":2}]},{"src":"willst (du)","target":[{"translation":"wottsch","count":1},{"translation":"Wottsch","count":1}]},{"src":"wir","target":[{"translation":"mir","count":1}]},{"src":"wird (er/sie/es)","target":[{"translation":"Wird","count":2}]},{"src":"wirklich","target":[{"translation":"Wirklich","count":2}]},{"src":"wissen","target":[{"translation":"wüsse","count":1}]},{"src":"witzig","target":[{"translation":"Witzig","count":1}]},{"src":"wo","target":[{"translation":"Wo","count":1}]},{"src":"woher","target":[{"translation":"Wohär","count":1}]},{"src":"zahlt (er/sie/es)","target":[{"translation":"Zaalt","count":1}]},{"src":"zeigst (du)","target":[{"translation":"Zeigsch","count":1}]},{"src":"zu leben","target":[{"translation":"z'läbe","count":1}]},{"src":"zuerst","target":[{"translation":"Zerscht","count":1}]},{"src":"Zürich","target":[{"translation":"Züri","count":1}]},{"src":"Zustände","target":[{"translation":"Zueständ","count":1}]},{"src":"Zwischenhändler","target":[{"translation":"Zwüschehändler","count":1}]}]