[{"src":"1","target":[{"translation":"eis","count":5}]},{"src":"10","target":[{"translation":"zäh","count":4},{"translation":"zä","count":1}]},{"src":"100","target":[{"translation":"hondert","count":4},{"translation":"hundert","count":1}]},{"src":"1000","target":[{"translation":"tuusig","count":5}]},{"src":"10000","target":[{"translation":"zähtuusig","count":4},{"translation":"zäätusig","count":1}]},{"src":"100000","target":[{"translation":"honderttuusig","count":3},{"translation":"honderttusig","count":1},{"translation":"hunderttuusig","count":1}]},{"src":"1000000","target":[{"translation":"en million","count":2},{"translation":"e million","count":1},{"translation":"eimilion","count":1},{"translation":"million","count":1}]},{"src":"1000000000","target":[{"translation":"e milliarde","count":1},{"translation":"eimiliard","count":1},{"translation":"en miliarde","count":1},{"translation":"en milliard","count":1},{"translation":"milliarde","count":1}]},{"src":"11","target":[{"translation":"elf","count":4},{"translation":"öuf","count":1}]},{"src":"12","target":[{"translation":"zwölf","count":4},{"translation":"zwöuf","count":1}]},{"src":"13","target":[{"translation":"drizäh","count":3},{"translation":"driizäh","count":1},{"translation":"drizä","count":1}]},{"src":"14","target":[{"translation":"vierzäh","count":4},{"translation":"vierzä","count":1}]},{"src":"15","target":[{"translation":"föfzäh","count":3},{"translation":"föfzä","count":1},{"translation":"füfzäh","count":1}]},{"src":"16","target":[{"translation":"sächzäh","count":2},{"translation":"sechzäh","count":1},{"translation":"sächszäh","count":1},{"translation":"sächzä","count":1}]},{"src":"17","target":[{"translation":"sebzäh","count":2},{"translation":"sebezä","count":1},{"translation":"sebezäh","count":1},{"translation":"siebzäh","count":1}]},{"src":"18","target":[{"translation":"achtzäh","count":3},{"translation":"achzä","count":1},{"translation":"achzäh","count":1}]},{"src":"19","target":[{"translation":"nünzäh","count":3},{"translation":"nünzä","count":1},{"translation":"nüünzäh","count":1}]},{"src":"2","target":[{"translation":"zwöi","count":3},{"translation":"zwei","count":1},{"translation":"zwoi","count":1}]},{"src":"20","target":[{"translation":"zwänzg","count":5}]},{"src":"3","target":[{"translation":"drü","count":4},{"translation":"drüü","count":1}]},{"src":"30","target":[{"translation":"drisg","count":2},{"translation":"drissg","count":2},{"translation":"driisg","count":1}]},{"src":"4","target":[{"translation":"vier","count":5}]},{"src":"40","target":[{"translation":"vierzg","count":5}]},{"src":"5","target":[{"translation":"füüf","count":4},{"translation":"füf","count":1}]},{"src":"50","target":[{"translation":"föfzg","count":4},{"translation":"füfzg","count":1}]},{"src":"6","target":[{"translation":"sächs","count":5}]},{"src":"60","target":[{"translation":"sächzg","count":5}]},{"src":"7","target":[{"translation":"sebe","count":4},{"translation":"sibe","count":1}]},{"src":"70","target":[{"translation":"sebezg","count":3},{"translation":"sebzg","count":1},{"translation":"siebezg","count":1}]},{"src":"8","target":[{"translation":"acht","count":5}]},{"src":"80","target":[{"translation":"achzg","count":3},{"translation":"achtzg","count":2}]},{"src":"9","target":[{"translation":"nüün","count":3},{"translation":"nün","count":2}]},{"src":"90","target":[{"translation":"nünzg","count":5}]},{"src":"Abenteuern","target":[{"translation":"abentür","count":1}]},{"src":"Alpenrose (Blume)","target":[{"translation":"auperoose","count":1}]},{"src":"Angeber","target":[{"translation":"plagööri","count":1}]},{"src":"Angst","target":[{"translation":"angscht","count":21}]},{"src":"Aufreisser","target":[{"translation":"schtächer","count":1}]},{"src":"Beschreibung","target":[{"translation":"beschreb","count":1}]},{"src":"Bilder","target":[{"translation":"belder","count":1}]},{"src":"Blumengesteck","target":[{"translation":"bluemegsteck","count":1}]},{"src":"Bursche","target":[{"translation":"boorscht","count":1},{"translation":"poorscht","count":1}]},{"src":"Dummschwätzer","target":[{"translation":"gaaggi","count":1}]},{"src":"Ehrenpreis (Blume)","target":[{"translation":"chatzenöigli","count":1}]},{"src":"Engel","target":[{"translation":"ängu","count":1}]},{"src":"Fenster","target":[{"translation":"fenster","count":1}]},{"src":"Frau","target":[{"translation":"frau","count":1},{"translation":"frou","count":1}]},{"src":"Fräulein","target":[{"translation":"fröili","count":1},{"translation":"frölein","count":1}]},{"src":"Gedankenschlund","target":[{"translation":"gedankeschlund","count":1}]},{"src":"Gespenstern","target":[{"translation":"gspenster","count":1}]},{"src":"Grund","target":[{"translation":"grond","count":1}]},{"src":"Hahnenfuss (Blume)","target":[{"translation":"ankeblüemli","count":1}]},{"src":"Hand","target":[{"translation":"hand","count":1}]},{"src":"Idiot","target":[{"translation":"tobu","count":1}]},{"src":"Jahresringen","target":[{"translation":"jahresrende","count":1}]},{"src":"Junge","target":[{"translation":"bueb","count":1},{"translation":"büebli","count":1},{"translation":"büebu","count":1}]},{"src":"Katze","target":[{"translation":"busle","count":1},{"translation":"büsi","count":1}]},{"src":"Kind","target":[{"translation":"chind","count":1}]},{"src":"Knutschfleck","target":[{"translation":"blööijele","count":1}]},{"src":"Kuss","target":[{"translation":"schmotz","count":1}]},{"src":"Köpfen","target":[{"translation":"chöpf","count":1}]},{"src":"Leben","target":[{"translation":"lebe","count":1}]},{"src":"Leute","target":[{"translation":"lüt","count":1}]},{"src":"Leuten","target":[{"translation":"lüt","count":1}]},{"src":"Liebchen","target":[{"translation":"gschpusi","count":1}]},{"src":"Liebe","target":[{"translation":"liebi","count":1}]},{"src":"Liebling","target":[{"translation":"häärzchäfer","count":1}]},{"src":"Luzerner","target":[{"translation":"lozärner","count":1}]},{"src":"Luzernerin","target":[{"translation":"lozärneri","count":1}]},{"src":"Löwenzahn (Blume)","target":[{"translation":"söiblueme","count":1}]},{"src":"Maiglöckchen (Blume)","target":[{"translation":"meijeriisli","count":1}]},{"src":"Mann","target":[{"translation":"maa","count":1}]},{"src":"Mitte","target":[{"translation":"mitti","count":1}]},{"src":"Mädchen","target":[{"translation":"gomsle","count":1},{"translation":"meitali","count":1},{"translation":"meitli","count":1},{"translation":"meitschi","count":1}]},{"src":"Nichtsnutz","target":[{"translation":"laaueri","count":1}]},{"src":"Ohrfeige geben","target":[{"translation":"e watsch ad ohre geh","count":1}]},{"src":"Pfingstrose (Blume)","target":[{"translation":"chéleroose","count":1}]},{"src":"Rand","target":[{"translation":"rand","count":1}]},{"src":"Runden","target":[{"translation":"rundene","count":1}]},{"src":"Samen","target":[{"translation":"sömli","count":1}]},{"src":"Schatten","target":[{"translation":"schatte","count":1}]},{"src":"Schlafzimmer","target":[{"translation":"s'juhee","count":1}]},{"src":"Schmeichelei","target":[{"translation":"schmuus","count":1}]},{"src":"Schätzchen","target":[{"translation":"müüsli","count":1},{"translation":"schätzali","count":1}]},{"src":"Segen","target":[{"translation":"säge","count":1}]},{"src":"Sekundenkleber","target":[{"translation":"schnellliim","count":4}]},{"src":"Sex mit Frauen-Geniesser","target":[{"translation":"meitschischmöcker","count":1}]},{"src":"Sex mit Männern-Geniesser","target":[{"translation":"buebeschmöcker","count":1}]},{"src":"Spaziergang","target":[{"translation":"spaziergang","count":1}]},{"src":"Stunde","target":[{"translation":"stund","count":2}]},{"src":"Taten","target":[{"translation":"tate","count":1}]},{"src":"Trottel","target":[{"translation":"lappi","count":1},{"translation":"latschi","count":1},{"translation":"lööli","count":1}]},{"src":"Tulpe (Blume)","target":[{"translation":"tolpe","count":1},{"translation":"toupe","count":1}]},{"src":"Typ","target":[{"translation":"kärli","count":1}]},{"src":"Urteil","target":[{"translation":"urteil","count":1}]},{"src":"Veilchen (Blume)","target":[{"translation":"veijali","count":1}]},{"src":"Verstand","target":[{"translation":"verstand","count":2}]},{"src":"Verstecken","target":[{"translation":"versteckis","count":1}]},{"src":"Wange","target":[{"translation":"bagge","count":1}]},{"src":"Wange (Liebkosung)","target":[{"translation":"liebali","count":1}]},{"src":"Wochen","target":[{"translation":"woche","count":1}]},{"src":"Wälder","target":[{"translation":"wälder","count":1}]},{"src":"Zeit","target":[{"translation":"ziit","count":4}]},{"src":"aber","target":[{"translation":"aber","count":5}]},{"src":"abhanden","target":[{"translation":"abhande","count":2}]},{"src":"abküssen","target":[{"translation":"abschmötzele","count":1},{"translation":"abschmötzle","count":1}]},{"src":"all","target":[{"translation":"all","count":1}]},{"src":"allen","target":[{"translation":"allne","count":1}]},{"src":"alles","target":[{"translation":"alles","count":3}]},{"src":"an","target":[{"translation":"a","count":1}]},{"src":"auch","target":[{"translation":"au","count":1}]},{"src":"auf","target":[{"translation":"uf","count":1}]},{"src":"auf dem","target":[{"translation":"ufem","count":1}]},{"src":"auf die (F)","target":[{"translation":"ofd","count":1}]},{"src":"aus","target":[{"translation":"us","count":1}]},{"src":"befingern","target":[{"translation":"aatööple","count":1}]},{"src":"begehrlich schauen","target":[{"translation":"guene","count":1}]},{"src":"begieriger Mensch","target":[{"translation":"glöschteler","count":1}]},{"src":"bei","target":[{"translation":"bi","count":1}]},{"src":"bin (ich)","target":[{"translation":"be","count":3}]},{"src":"bin ich","target":[{"translation":"beni","count":3}]},{"src":"bis ich es","target":[{"translation":"bessis","count":1}]},{"src":"bist (du)","target":[{"translation":"bisch","count":4},{"translation":"bésch","count":3}]},{"src":"blind","target":[{"translation":"blind","count":3}]},{"src":"bricht (er/sie/es)","target":[{"translation":"brecht","count":4}]},{"src":"da","target":[{"translation":"do","count":4}]},{"src":"dagegen","target":[{"translation":"degege","count":1}]},{"src":"das","target":[{"translation":"das","count":6},{"translation":"wo","count":4}]},{"src":"das ich","target":[{"translation":"s’ech","count":2}]},{"src":"dass","target":[{"translation":"dass","count":7}]},{"src":"dass ich","target":[{"translation":"dassi","count":1}]},{"src":"deine (F)","target":[{"translation":"dini","count":1}]},{"src":"deiner (M)","target":[{"translation":"diine","count":1}]},{"src":"dem","target":[{"translation":"dem","count":3}]},{"src":"den (pl.)","target":[{"translation":"dene","count":1}]},{"src":"deswegen","target":[{"translation":"wäg dem","count":1}]},{"src":"dich","target":[{"translation":"dich","count":3},{"translation":"dech","count":1},{"translation":"di","count":1}]},{"src":"die (F)","target":[{"translation":"wo","count":1}]},{"src":"die (pl.)","target":[{"translation":"die","count":4},{"translation":"wo","count":2}]},{"src":"dir","target":[{"translation":"dir","count":2}]},{"src":"doch","target":[{"translation":"doch","count":3}]},{"src":"du","target":[{"translation":"du","count":7}]},{"src":"du hast","target":[{"translation":"hesch","count":1}]},{"src":"dumme Frau","target":[{"translation":"zwätschge","count":1}]},{"src":"dummer Schnorrer","target":[{"translation":"blòòschti","count":1}]},{"src":"ein (M)","target":[{"translation":"e","count":2}]},{"src":"ein (N)","target":[{"translation":"es","count":2}]},{"src":"ein kleines bisschen","target":[{"translation":"es bérebétzali","count":1}]},{"src":"eine (F)","target":[{"translation":"e","count":1}]},{"src":"einen","target":[{"translation":"en","count":1}]},{"src":"einen Partner finden","target":[{"translation":"onder d'huube cho","count":1}]},{"src":"einfältige Frau","target":[{"translation":"domms beeri","count":1}]},{"src":"einige Zeit","target":[{"translation":"zitli","count":1}]},{"src":"er","target":[{"translation":"er","count":1}]},{"src":"es","target":[{"translation":"es","count":1}]},{"src":"es funkt","target":[{"translation":"es chnöschperlet","count":1}]},{"src":"es hat","target":[{"translation":"s’hed","count":1}]},{"src":"es ist","target":[{"translation":"s'ésch","count":1}]},{"src":"etwas","target":[{"translation":"öppis","count":4}]},{"src":"finde (ich)","target":[{"translation":"fend","count":4}]},{"src":"flirten","target":[{"translation":"karichäschperle","count":1},{"translation":"karisiere","count":1}]},{"src":"flott","target":[{"translation":"tschènt","count":1}]},{"src":"für","target":[{"translation":"för","count":1},{"translation":"für","count":1}]},{"src":"gar","target":[{"translation":"gar","count":1}]},{"src":"gebe (ich)","target":[{"translation":"gib","count":1}]},{"src":"geben (sie)","target":[{"translation":"gänd","count":1}]},{"src":"gedreht","target":[{"translation":"dreht","count":1}]},{"src":"gefunden","target":[{"translation":"gfunde","count":1}]},{"src":"gefällst (du)","target":[{"translation":"gfausch","count":1}]},{"src":"gefällt","target":[{"translation":"gfällt","count":1}]},{"src":"gefällten (pl.)","target":[{"translation":"gfällte","count":1}]},{"src":"gegangen","target":[{"translation":"gange","count":1}]},{"src":"geht (er/sie/es)","target":[{"translation":"gaht","count":1}]},{"src":"gekommen","target":[{"translation":"cho","count":2}]},{"src":"getroffen","target":[{"translation":"troffe","count":1}]},{"src":"glaube ich","target":[{"translation":"glaubi","count":1}]},{"src":"grossartig","target":[{"translation":"böimig","count":1}]},{"src":"grossartiger (M)","target":[{"translation":"böimige","count":1}]},{"src":"grummlige Person (niedlich)","target":[{"translation":"brommli","count":1},{"translation":"brommlibär","count":1}]},{"src":"gut","target":[{"translation":"guet","count":1}]},{"src":"gut aussehen","target":[{"translation":"gattig mache","count":1}]},{"src":"habe (ich)","target":[{"translation":"ha","count":3},{"translation":"han","count":2}]},{"src":"habe ich","target":[{"translation":"hani","count":17}]},{"src":"halten","target":[{"translation":"hebe","count":1}]},{"src":"hast (du)","target":[{"translation":"hesch","count":1}]},{"src":"heiraten","target":[{"translation":"hüroote","count":1}]},{"src":"herziges Mädchen","target":[{"translation":"chrogali","count":1}]},{"src":"hundert","target":[{"translation":"hondert","count":1}]},{"src":"hässlich","target":[{"translation":"wüescht","count":1}]},{"src":"hören (sie)","target":[{"translation":"ghöred","count":1}]},{"src":"hörst (du)","target":[{"translation":"ghörsch","count":1}]},{"src":"hübsche Person","target":[{"translation":"schnétz","count":1},{"translation":"schoss","count":1}]},{"src":"ich","target":[{"translation":"ech","count":15},{"translation":"ich","count":2},{"translation":"i","count":1}]},{"src":"ich habe","target":[{"translation":"han","count":1}]},{"src":"ich habe es","target":[{"translation":"has","count":1}]},{"src":"ich mache","target":[{"translation":"mach","count":1}]},{"src":"ich stehe","target":[{"translation":"stahne","count":1}]},{"src":"ich suche","target":[{"translation":"sueche","count":1}]},{"src":"ich versuche","target":[{"translation":"versuech","count":1}]},{"src":"ich weiss","target":[{"translation":"weiss","count":2}]},{"src":"im","target":[{"translation":"im","count":1}]},{"src":"immer","target":[{"translation":"immer","count":1}]},{"src":"in","target":[{"translation":"i","count":3}]},{"src":"in der","target":[{"translation":"ide","count":1}]},{"src":"in der nacht den Schatz besuchen","target":[{"translation":"fëischterle","count":1}]},{"src":"in die (F)","target":[{"translation":"id","count":1}]},{"src":"ist (er/sie/es)","target":[{"translation":"isch","count":2},{"translation":"ésch","count":2}]},{"src":"ja","target":[{"translation":"ja","count":1}]},{"src":"kann ich","target":[{"translation":"chani","count":1}]},{"src":"klebt (er/sie/es)","target":[{"translation":"chläbt","count":4}]},{"src":"kämpft (er/sie/es)","target":[{"translation":"kämpft","count":1}]},{"src":"könnte (er/sie/es)","target":[{"translation":"chönnt","count":1}]},{"src":"küssen","target":[{"translation":"schmötzele","count":1}]},{"src":"langandauernde Liebschaft","target":[{"translation":"gschlëipf","count":1}]},{"src":"lange","target":[{"translation":"lang","count":2}]},{"src":"laute Person","target":[{"translation":"läärmi","count":1}]},{"src":"leben","target":[{"translation":"lebe","count":1}]},{"src":"lehn (du)","target":[{"translation":"lehn","count":1}]},{"src":"lieb","target":[{"translation":"gäärn","count":1}]},{"src":"liebe (ich)","target":[{"translation":"liebe","count":2}]},{"src":"liebkosen","target":[{"translation":"schätzele","count":1}]},{"src":"lieblich schauen","target":[{"translation":"lüegele","count":1}]},{"src":"locken","target":[{"translation":"zöiggle","count":1}]},{"src":"mache (ich)","target":[{"translation":"mach","count":3}]},{"src":"mehr","target":[{"translation":"meh","count":7}]},{"src":"mein (N)","target":[{"translation":"min","count":1},{"translation":"mis","count":1}]},{"src":"meinem","target":[{"translation":"mim","count":1}]},{"src":"mich","target":[{"translation":"mech","count":7},{"translation":"mich","count":2},{"translation":"mi","count":1}]},{"src":"mir","target":[{"translation":"mer","count":6},{"translation":"mir","count":1}]},{"src":"mit","target":[{"translation":"met","count":9},{"translation":"mit","count":1}]},{"src":"mit Nachbar*in Kontakt suchen","target":[{"translation":"nööchberle","count":1}]},{"src":"nach","target":[{"translation":"nach","count":2}]},{"src":"neuen (M)","target":[{"translation":"neue","count":1}]},{"src":"nicht","target":[{"translation":"ned","count":11},{"translation":"nie","count":8},{"translation":"nöd","count":7}]},{"src":"nicht mehr","target":[{"translation":"nüm","count":2},{"translation":"nömme","count":1},{"translation":"nümme","count":1}]},{"src":"nie","target":[{"translation":"nie","count":1}]},{"src":"nimm es (du)","target":[{"translation":"nimms","count":1}]},{"src":"noch","target":[{"translation":"no","count":2}]},{"src":"näher","target":[{"translation":"nööcher","count":1}]},{"src":"ob ich","target":[{"translation":"obi","count":1}]},{"src":"offenen (pl.)","target":[{"translation":"offene","count":1}]},{"src":"ohne","target":[{"translation":"ohni","count":3}]},{"src":"perfekten (N)","target":[{"translation":"perfekte","count":1}]},{"src":"plötzlich","target":[{"translation":"plötzlech","count":1}]},{"src":"schaue (ich)","target":[{"translation":"lueg","count":1}]},{"src":"schlimm","target":[{"translation":"schlimm","count":1}]},{"src":"schmusen","target":[{"translation":"schmuse","count":1}]},{"src":"schon","target":[{"translation":"scho","count":2}]},{"src":"schwebe (ich)","target":[{"translation":"schwäbe","count":1}]},{"src":"schön","target":[{"translation":"schön","count":1}]},{"src":"schönen (pl.)","target":[{"translation":"schöne","count":1}]},{"src":"sehr","target":[{"translation":"cheibe","count":1}]},{"src":"selber","target":[{"translation":"sälber","count":2}]},{"src":"sich","target":[{"translation":"sech","count":3}]},{"src":"sich zaghaft annähern","target":[{"translation":"merkehocke","count":1}]},{"src":"soll (ich)","target":[{"translation":"söt","count":3}]},{"src":"sonst","target":[{"translation":"sosch","count":1},{"translation":"susch","count":1}]},{"src":"spielt (er/sie/es)","target":[{"translation":"spillt","count":1}]},{"src":"sprachlos","target":[{"translation":"sprochlos","count":1}]},{"src":"spriessen","target":[{"translation":"spriesse","count":1}]},{"src":"stehe (ich)","target":[{"translation":"ston","count":1}]},{"src":"suche (ich)","target":[{"translation":"suech","count":1}]},{"src":"sympathisch","target":[{"translation":"gmögig","count":1},{"translation":"gäbig","count":1}]},{"src":"sympatische (F)","target":[{"translation":"gmögigi","count":1}]},{"src":"sympatischer (M)","target":[{"translation":"gäbige","count":1}]},{"src":"süsser Typ","target":[{"translation":"schnügu","count":1},{"translation":"schnüsu","count":1}]},{"src":"tanz (du)","target":[{"translation":"tanz","count":1}]},{"src":"tanzfreudige Person","target":[{"translation":"tanzfödle","count":1}]},{"src":"tollen (N)","target":[{"translation":"tolle","count":1}]},{"src":"traue (ich)","target":[{"translation":"trou","count":1}]},{"src":"trotzdem","target":[{"translation":"trotzdem","count":1}]},{"src":"tun (sie)","target":[{"translation":"tüend","count":1}]},{"src":"türmen (sie)","target":[{"translation":"törmed","count":1}]},{"src":"um","target":[{"translation":"um","count":1}]},{"src":"und","target":[{"translation":"und","count":9},{"translation":"ond","count":5}]},{"src":"vergeben","target":[{"translation":"vergebe","count":1}]},{"src":"verkrochen","target":[{"translation":"verchroche","count":1}]},{"src":"verlassen","target":[{"translation":"verlah","count":1}]},{"src":"verschwunden","target":[{"translation":"verschwunde","count":1}]},{"src":"verstehen","target":[{"translation":"verstah","count":1}]},{"src":"verstehst du","target":[{"translation":"verstahsch","count":2}]},{"src":"von","target":[{"translation":"vo","count":2}]},{"src":"vor allem","target":[{"translation":"vorallem","count":12},{"translation":"vor allem","count":5}]},{"src":"vor einem","target":[{"translation":"voreme","count":1}]},{"src":"was","target":[{"translation":"wo","count":2},{"translation":"was","count":1}]},{"src":"was ich","target":[{"translation":"woni","count":4},{"translation":"wasi","count":3}]},{"src":"weil","target":[{"translation":"wel","count":1}]},{"src":"weiter","target":[{"translation":"witer","count":1}]},{"src":"wenn ich","target":[{"translation":"wenni","count":3}]},{"src":"widersetzt (er/sie/es)","target":[{"translation":"wedersetzt","count":1}]},{"src":"will (ich)","target":[{"translation":"wet","count":2},{"translation":"wett","count":2}]},{"src":"wirklich","target":[{"translation":"werklech","count":3}]},{"src":"wo","target":[{"translation":"wo","count":1}]},{"src":"wollen","target":[{"translation":"welle","count":1}]},{"src":"wäre (er/sie/es)","target":[{"translation":"wär","count":1}]},{"src":"zu","target":[{"translation":"zu","count":2}]},{"src":"zu Ende","target":[{"translation":"z'änd","count":1}]},{"src":"zu bewegen","target":[{"translation":"z’bewege","count":1}]},{"src":"zu erfüllen","target":[{"translation":"z’erfölle","count":1}]},{"src":"zu suchen","target":[{"translation":"z’sueche","count":1}]},{"src":"zuhören (sie)","target":[{"translation":"losed","count":1}]},{"src":"zusammenpassen","target":[{"translation":"zämepasse","count":1}]},{"src":"zwar","target":[{"translation":"zwar","count":1}]},{"src":"über","target":[{"translation":"öber","count":1}]}]